azure/mgmt/managedservices/__init__.py
azure/mgmt/managedservices/_configuration.py
azure/mgmt/managedservices/_managed_services_client.py
azure/mgmt/managedservices/_version.py
azure/mgmt/managedservices/aio/__init__.py
azure/mgmt/managedservices/aio/_configuration.py
azure/mgmt/managedservices/aio/_managed_services_client.py
azure/mgmt/managedservices/aio/operations/__init__.py
azure/mgmt/managedservices/aio/operations/_marketplace_registration_definitions_operations.py
azure/mgmt/managedservices/aio/operations/_marketplace_registration_definitions_without_scope_operations.py
azure/mgmt/managedservices/aio/operations/_operations.py
azure/mgmt/managedservices/aio/operations/_registration_assignments_operations.py
azure/mgmt/managedservices/aio/operations/_registration_definitions_operations.py
azure/mgmt/managedservices/models/__init__.py
azure/mgmt/managedservices/models/_managed_services_client_enums.py
azure/mgmt/managedservices/models/_models.py
azure/mgmt/managedservices/models/_models_py3.py
azure/mgmt/managedservices/operations/__init__.py
azure/mgmt/managedservices/operations/_marketplace_registration_definitions_operations.py
azure/mgmt/managedservices/operations/_marketplace_registration_definitions_without_scope_operations.py
azure/mgmt/managedservices/operations/_operations.py
azure/mgmt/managedservices/operations/_registration_assignments_operations.py
azure/mgmt/managedservices/operations/_registration_definitions_operations.py
azure_mgmt_managedservices-6.0.0.dist-info/METADATA
azure_mgmt_managedservices-6.0.0.dist-info/WHEEL
azure_mgmt_managedservices-6.0.0.dist-info/top_level.txt
azure_mgmt_managedservices-6.0.0.dist-info/RECORD
